colosseum/.gitignore
colosseum/__init__.py
colosseum/agent.py
colosseum/games/__init__.py
colosseum/games/food_catcher/DOCS.md
colosseum/games/food_catcher/__init__.py
colosseum/games/food_catcher/actor.py
colosseum/games/food_catcher/base.py
colosseum/games/food_catcher/config.py
colosseum/games/food_catcher/food.py
colosseum/games/food_catcher/game.py
colosseum/games/food_catcher/tests/__init__.py
colosseum/games/food_catcher/tests/test_actor.py
colosseum/games/food_catcher/tests/test_base.py
colosseum/games/food_catcher/tests/test_food.py
colosseum/manager.py
colosseum/match.py
colosseum/tests/__init__.py
colosseum/tests/test_utils.py
colosseum/tournament.py
colosseum/tournament_online.py
colosseum/utils.py
colosseum/watchdog.py
colosseum_arena-0.1.1.dist-info/LICENSE
colosseum_arena-0.1.1.dist-info/WHEEL
colosseum_arena-0.1.1.dist-info/METADATA
colosseum_arena-0.1.1.dist-info/RECORD
