Metadata-Version: 2.1
Name: colosseum-arena
Version: 0.1.1
Summary: An AI arena, where agents fight each other
Home-page: https://www.colosseum.website/
License: MIT
Keywords: automated-tournaments,multi-agents
Author: h3nnn4n
Author-email: colosseum@h3nnn4n.me
Requires-Python: >=3.10,<3.11
Classifier: Development Status :: 4 - Beta
Classifier: Intended Audience :: Developers
Classifier: License :: OSI Approved :: MIT License
Classifier: Programming Language :: Python :: 3
Classifier: Programming Language :: Python :: 3.10
Requires-Dist: numpy (>=1.21.4,<2.0.0)
Requires-Dist: pexpect (>=4.8.0,<5.0.0)
Requires-Dist: python-dotenv (>=0.19.2,<0.20.0)
Requires-Dist: requests (>=2.26.0,<3.0.0)
Requires-Dist: simple-elo (>=0.1.1,<0.2.0)
Project-URL: Bug Tracker, https://github.com/h3nnn4n/colosseum/issues
Project-URL: Repository, https://github.com/h3nnn4n/colosseum/
Project-URL: Website, https://www.colosseum.website
